ot2rec_report/__init__.py
ot2rec_report/main.py
ot2rec_report/utils.py
ot2rec_report/templates/__init__.py
ot2rec_report/templates/report_aretomo_align.ipynb
ot2rec_report/templates/report_aretomo_header.ipynb
ot2rec_report/templates/report_aretomo_recon.ipynb
ot2rec_report/templates/report_ctffind.ipynb
ot2rec_report/templates/report_ctfsim.ipynb
ot2rec_report/templates/report_excludebadtilts.ipynb
ot2rec_report/templates/report_imod_align.ipynb
ot2rec_report/templates/report_imod_header.ipynb
ot2rec_report/templates/report_imod_recon.ipynb
ot2rec_report/templates/report_main.ipynb
ot2rec_report/templates/report_mc.ipynb
ot2rec_report/templates/report_rlf_deconv.ipynb
ot2rec_report/templates/report_savu_recon.ipynb
ot2rec_report/templates/report_warp.ipynb
ot2rec_report/templates/workflow_diagram.ipynb
ot2rec_report-0.1.0.post4.data/data/templates/report_aretomo_align.ipynb
ot2rec_report-0.1.0.post4.data/data/templates/report_aretomo_header.ipynb
ot2rec_report-0.1.0.post4.data/data/templates/report_aretomo_recon.ipynb
ot2rec_report-0.1.0.post4.data/data/templates/report_ctffind.ipynb
ot2rec_report-0.1.0.post4.data/data/templates/report_ctfsim.ipynb
ot2rec_report-0.1.0.post4.data/data/templates/report_excludebadtilts.ipynb
ot2rec_report-0.1.0.post4.data/data/templates/report_imod_align.ipynb
ot2rec_report-0.1.0.post4.data/data/templates/report_imod_header.ipynb
ot2rec_report-0.1.0.post4.data/data/templates/report_imod_recon.ipynb
ot2rec_report-0.1.0.post4.data/data/templates/report_main.ipynb
ot2rec_report-0.1.0.post4.data/data/templates/report_mc.ipynb
ot2rec_report-0.1.0.post4.data/data/templates/report_rlf_deconv.ipynb
ot2rec_report-0.1.0.post4.data/data/templates/report_savu_recon.ipynb
ot2rec_report-0.1.0.post4.data/data/templates/report_warp.ipynb
ot2rec_report-0.1.0.post4.data/data/templates/workflow_diagram.ipynb
ot2rec_report-0.1.0.post4.dist-info/LICENSE
ot2rec_report-0.1.0.post4.dist-info/METADATA
ot2rec_report-0.1.0.post4.dist-info/WHEEL
ot2rec_report-0.1.0.post4.dist-info/entry_points.txt
ot2rec_report-0.1.0.post4.dist-info/top_level.txt
ot2rec_report-0.1.0.post4.dist-info/RECORD
